pygantt/__init__.py
pygantt/cli.py
pygantt/pygantt.py
pygantt/util.py
pygantt-0.1.2.dist-info/DESCRIPTION.rst
pygantt-0.1.2.dist-info/METADATA
pygantt-0.1.2.dist-info/RECORD
pygantt-0.1.2.dist-info/WHEEL
pygantt-0.1.2.dist-info/entry_points.txt
pygantt-0.1.2.dist-info/metadata.json
pygantt-0.1.2.dist-info/top_level.txt
