Metadata-Version: 2.0
Name: pygantt
Version: 0.1.2
Summary: Gantt charts in python
Home-page: https://github.com/pygantt/pygantt
Author: PyGantt developers
Author-email: seth.mridul@gmail.com
License: BSD license
Keywords: pygantt
Platform: UNKNOWN
Classifier: Development Status :: 2 - Pre-Alpha
Classifier: Intended Audience :: Developers
Classifier: License :: OSI Approved :: BSD License
Classifier: Natural Language :: English
Classifier: Programming Language :: Python :: 3
Classifier: Programming Language :: Python :: 3.4
Classifier: Programming Language :: Python :: 3.5
Classifier: Programming Language :: Python :: 3.6
Requires-Dist: Click (>=6.0)
Requires-Dist: pandas (>=0.18)
Requires-Dist: matplotlib
Requires-Dist: numpy
